MANIFEST.in
README.md
requirements.txt
setup.cfg
setup.py
fastflownet/__init__.py
fastflownet/data.py
fastflownet/model.py
fastflownet/visualization.py
fastflownet.egg-info/PKG-INFO
fastflownet.egg-info/SOURCES.txt
fastflownet.egg-info/dependency_links.txt
fastflownet.egg-info/not-zip-safe
fastflownet.egg-info/requires.txt
fastflownet.egg-info/top_level.txt
fastflownet/correlation_package/__init__.py
fastflownet/correlation_package/correlation.py
fastflownet/correlation_package/correlation_cuda.cc
fastflownet/correlation_package/correlation_cuda_kernel.cu
fastflownet/correlation_package/correlation_cuda_kernel.cuh